tdextensions/__init__.py
tdextensions/distributed/__init__.py
tdextensions/distributed/distdataframe.py
tdextensions/distributed/wrappers/sto.j2
tdextensions-1.0.0rc1.dist-info/LICENSE.txt
tdextensions-1.0.0rc1.dist-info/METADATA
tdextensions-1.0.0rc1.dist-info/WHEEL
tdextensions-1.0.0rc1.dist-info/top_level.txt
tdextensions-1.0.0rc1.dist-info/RECORD
