Metadata-Version: 2.1
Name: tdextensions
Version: 1.0.0rc1
Summary: Teradata Consulting Python Client Extensions
Home-page: UNKNOWN
Author: Teradata
Author-email: teradata.corporation@teradatacorporation.com
License: UNKNOWN
Platform: UNKNOWN
Requires-Python: >=3.6.0
Requires-Dist: jinja2 (>=2.10)
Requires-Dist: teradataml (>=16.20.0.3)
Requires-Dist: dill (>=0.2.8.2)
